frage/__init__.py
frage/__main__.py
frage/compiler.py
frage/config.py
frage/http.py
frage/models.py
frage/parser.py
frage-0.3.0.dist-info/entry_points.txt
frage-0.3.0.dist-info/LICENSE
frage-0.3.0.dist-info/WHEEL
frage-0.3.0.dist-info/METADATA
frage-0.3.0.dist-info/RECORD
